data_experiment/__init__.py
data_experiment/data_handle.py
data_experiment/data_reviewer.py
generate_verification/__init__.py
generate_verification/use_captcha.py
generate_verification/use_gvcode.py
rpa_ocr/__init__.py
rpa_ocr/Identify_English/__init__.py
rpa_ocr/Identify_English/crnn_model.py
rpa_ocr/Identify_English/inference.py
rpa_ocr/Identify_English/lr_scheduler.py
rpa_ocr/Identify_English/rawdataset.py
rpa_ocr/Identify_English/train_tools.py
rpa_ocr/Identify_English/use_alphabet.py
rpa_ocr/deploy_win32/__init__.py
rpa_ocr/deploy_win32/model2onnx.py
rpa_ocr/deploy_win32/oonx_infer.py
rpa_ocr/deploy_win32/test_oonx.py
rpa_ocr/verification_service/__init__.py
rpa_ocr/verification_service/main_service.py
rpa_ocr/verification_service/test_captcha.py
rpa_ocr/verification_service/test_upload_model.py
rpa_ocr/verification_service/upload_model.py
rpa_ocr/verification_service/verification_main.py
rpa_ocr-0.2.1.dist-info/LICENSE
rpa_ocr-0.2.1.dist-info/METADATA
rpa_ocr-0.2.1.dist-info/WHEEL
rpa_ocr-0.2.1.dist-info/top_level.txt
rpa_ocr-0.2.1.dist-info/RECORD
