Metadata-Version: 2.1
Name: rpa-ocr
Version: 0.2.1
Summary: A Tools for use algorithm for verification recognition
Home-page: https://code.ii-ai.tech/zhutaonan/rpa_verification.git
Author: adolf
Author-email: adolf1321794021@gmail.com
License: UNKNOWN
Platform: UNKNOWN
Classifier: Programming Language :: Python :: 3
Classifier: License :: OSI Approved :: MIT License
Classifier: Operating System :: OS Independent
Requires-Dist: torch
Requires-Dist: torchvision
Requires-Dist: opencv-python
Requires-Dist: pyyaml
Requires-Dist: tqdm
